README.md
setup.py
sb_dev_tools/FactoryMixin.py
sb_dev_tools/PolyFactory.py
sb_dev_tools/SnoodlebootError.py
sb_dev_tools/__init__.py
sb_dev_tools.egg-info/PKG-INFO
sb_dev_tools.egg-info/SOURCES.txt
sb_dev_tools.egg-info/dependency_links.txt
sb_dev_tools.egg-info/top_level.txt
test/TestPolyFactory.py
test/__init__.py